drove-0.3.dist-info/RECORD
drove-0.3.dist-info/METADATA
drove-0.3.dist-info/top_level.txt
drove-0.3.dist-info/DESCRIPTION.rst
drove-0.3.dist-info/metadata.json
drove-0.3.dist-info/WHEEL
drove-0.3.dist-info/entry_points.txt
drove/package.py
drove/channel.py
drove/reloader.py
drove/__init__.py
drove/script.py
drove/plugin.py
drove/config.py
drove/data/value.py
drove/data/event.py
drove/data/__init__.py
drove/config/drove.conf
drove/util/importer.py
drove/util/timer.py
drove/util/temp.py
drove/util/__init__.py
drove/util/tester.py
drove/util/signature.py
drove/util/log.py
drove/util/lexer.py
drove/util/network.py
drove/util/daemon/__init__.py
drove/util/daemon/posix.py
drove/tests/test_command.py
drove/tests/test_package.py
drove/tests/test_config.py
drove/tests/__init__.py
drove/tests/test_plugin.py
drove/tests/test_reloader.py
drove/tests/test_channel.py
drove/tests/data/test_event.py
drove/tests/data/test_data.py
drove/tests/data/test_value.py
drove/tests/data/__init__.py
drove/tests/util/test_signature.py
drove/tests/util/test_timer.py
drove/tests/util/test_network.py
drove/tests/util/test_daemon.py
drove/tests/util/test_log.py
drove/tests/util/test_tester.py
drove/tests/util/test_lexer.py
drove/tests/util/__init__.py
drove/tests/util/test_temp.py
drove/tests/util/test_importer.py
drove/tests/command/test_search.py
drove/tests/command/test_list.py
drove/tests/command/test_remove.py
drove/tests/command/__init__.py
drove/tests/command/test_install.py
drove/command/daemon.py
drove/command/remove.py
drove/command/__init__.py
drove/command/list.py
drove/command/install.py
drove/command/search.py
drove/plugins/internal.log.version
drove/plugins/internal/__init__.pyc
drove/plugins/internal/__init__.py
drove/plugins/internal/__pycache__/__init__.cpython-34.pyc
drove/plugins/internal/log/log.pyc
drove/plugins/internal/log/test_log.pyc
drove/plugins/internal/log/test_log.py
drove/plugins/internal/log/__init__.pyc
drove/plugins/internal/log/__init__.py
drove/plugins/internal/log/log.py
drove/plugins/internal/log/__pycache__/test_log.cpython-34.pyc
drove/plugins/internal/log/__pycache__/__init__.cpython-34.pyc
