Metadata-Version: 2.0
Name: drove
Version: 0.3
Summary: Monitoring and statistical analysis system for a drove of systems
Home-page: http://drove.io
Author: Andrés J. Díaz
Author-email: ajdiaz@connectical.com
License: GPL3
Platform: UNKNOWN
Classifier: Development Status :: 4 - Beta
Classifier: Intended Audience :: Developers
Classifier: Natural Language :: English
Classifier: License :: OSI Approved :: GNU General Public License v3 (GPLv3)
Classifier: Development Status :: 4 - Beta
Classifier: Programming Language :: Python :: 2.7
Classifier: Programming Language :: Python :: 3.4
Classifier: Operating System :: OS Independent
Classifier: Programming Language :: Python
Requires-Dist: six (>=1.8.0)
Requires-Dist: wcfg (>=3)
